bipartite_learn/__init__.py
bipartite_learn/_version.py
bipartite_learn/base.py
bipartite_learn/melter.py
bipartite_learn/neighbors.py
bipartite_learn/pipeline.py
bipartite_learn/wrappers.py
bipartite_learn/datasets/__init__.py
bipartite_learn/datasets/_dpi_yamanishi.py
bipartite_learn/datasets/base.py
bipartite_learn/datasets/loader.py
bipartite_learn/ensemble/__init__.py
bipartite_learn/ensemble/_forest.py
bipartite_learn/ensemble/_gb.py
bipartite_learn/ensemble/_semisupervised_forest.py
bipartite_learn/matrix_factorization/__init__.py
bipartite_learn/matrix_factorization/_dnilmf.py
bipartite_learn/matrix_factorization/_nrlmf.py
bipartite_learn/metrics/__init__.py
bipartite_learn/model_selection/__init__.py
bipartite_learn/model_selection/_search.py
bipartite_learn/model_selection/_split.py
bipartite_learn/model_selection/_validation.py
bipartite_learn/preprocessing/__init__.py
bipartite_learn/preprocessing/monopartite.py
bipartite_learn/preprocessing/multipartite.py
bipartite_learn/tree/__init__.py
bipartite_learn/tree/_axis_criterion.cp311-win_amd64.pyd
bipartite_learn/tree/_bipartite_classes.py
bipartite_learn/tree/_bipartite_criterion.cp311-win_amd64.pyd
bipartite_learn/tree/_bipartite_splitter.cp311-win_amd64.pyd
bipartite_learn/tree/_bipartite_tree.cp311-win_amd64.pyd
bipartite_learn/tree/_semisupervised_classes.py
bipartite_learn/tree/_semisupervised_criterion.cp311-win_amd64.pyd
bipartite_learn/tree/_splitter_factory.py
bipartite_learn/tree/_unsupervised_criterion.cp311-win_amd64.pyd
bipartite_learn/utils/__init__.py
bipartite_learn/utils/_param_validation.py
bipartite_learn/utils/discovery.py
tests/__init__.py
tests/benchmark_gso_strategies.py
tests/meta_test.py
tests/setup.py
tests/test_all_estimators.py
tests/test_bipartite_cross_validation.py
tests/test_bipartite_trees.py
tests/test_compare_monopartite_bipartite.py
tests/test_criteria.py
tests/test_datasets.py
tests/test_default_parameters.py
tests/test_ensembles.py
tests/test_gradient_boosting.py
bipartite_learn-0.7.5.dist-info/LICENSE
bipartite_learn-0.7.5.dist-info/METADATA
bipartite_learn-0.7.5.dist-info/WHEEL
bipartite_learn-0.7.5.dist-info/top_level.txt
bipartite_learn-0.7.5.dist-info/RECORD
