Metadata-Version: 2.1
Name: bipartite_learn
Version: 0.7.5
Summary: Machine learning estimators for bipartite data.
Home-page: http://github.com/pedroilidio/bipartite_learn
Author: Pedro Ilídio
Author-email: pedrilidio@gmail.com
License: new BSD
License-File: LICENSE
Requires-Dist: cython==0.29.33
Requires-Dist: scikit-learn==1.3.0
Requires-Dist: numpy==1.26.4
Requires-Dist: imbalanced-learn==0.9.1
Provides-Extra: docs
Requires-Dist: sphinx; extra == "docs"
Requires-Dist: pydata-sphinx-theme; extra == "docs"
